cmake_4_1_0_win_x64_p1
