Metadata-Version: 2.4
Name: cmake_4_1_0_win_x64_p1
Version: 4.1.0
Summary: Segment cmake-4.1.0-windows-x86_64 part p1
License-Expression: MIT
